editor/__init__.py
editor/__main__.py
editor/app.py
editor/cli.py
editor/files.py
editor/inspector.py
editor/render.py
editor/resources.py
editor/splash.py
editor/views.py
editor/window.py
editor/icons/icon.png
editor/icons/splash.png
editor/icons/buttons/pause.png
editor/icons/buttons/play.png
editor/icons/buttons/stop.png
editor/icons/console/error.png
editor/icons/console/info.png
editor/icons/console/output.png
editor/icons/console/template.png
editor/icons/console/warning.png
editor/icons/inspector/add.png
editor/icons/inspector/logo.png
editor/theme/dark.qss
editor/theme/light.qss
pyunity_editor-0.1.1.dist-info/LICENSE
pyunity_editor-0.1.1.dist-info/METADATA
pyunity_editor-0.1.1.dist-info/WHEEL
pyunity_editor-0.1.1.dist-info/entry_points.txt
pyunity_editor-0.1.1.dist-info/top_level.txt
pyunity_editor-0.1.1.dist-info/RECORD
