Metadata-Version: 2.1
Name: pyunity-editor
Version: 0.1.1
Summary: An Editor for PyUnity in the style of the UnityEditor
Home-page: https://github.com/pyunity/pyunity-gui
Author: Ray Chen
Author-email: tankimarshal2@gmail.com
License: UNKNOWN
Platform: UNKNOWN
Classifier: Development Status :: 3 - Alpha
Classifier: Natural Language :: English
Classifier: License :: OSI Approved :: MIT License
Classifier: Operating System :: MacOS
Classifier: Operating System :: Microsoft :: Windows
Classifier: Operating System :: POSIX :: Linux
Classifier: Programming Language :: Python :: 3
Requires-Python: >=3
License-File: LICENSE
Requires-Dist: pyunity
Requires-Dist: pyqt5
Requires-Dist: pillow
